funapi/__init__.py
fungithub-0.0.1.dist-info/LICENSE
fungithub-0.0.1.dist-info/METADATA
fungithub-0.0.1.dist-info/WHEEL
fungithub-0.0.1.dist-info/entry_points.txt
fungithub-0.0.1.dist-info/top_level.txt
fungithub-0.0.1.dist-info/RECORD
